CircuitNotionAI/__init__.py
circuitnotionai-0.1.4.dist-info/licenses/LICENSE
circuitnotionai-0.1.4.dist-info/METADATA
circuitnotionai-0.1.4.dist-info/WHEEL
circuitnotionai-0.1.4.dist-info/top_level.txt
circuitnotionai-0.1.4.dist-info/RECORD
