Metadata-Version: 2.4
Name: CircuitNotionAI
Version: 0.1.4
Summary: A Python client for the CircuitNotion AI API
Author-email: ntirushwajeanmarc <ntirushwajeanmarc@gmail.com>
Requires-Python: >=3.7
License-File: LICENSE
Requires-Dist: requests>=2.25.0
Dynamic: license-file
